pda_anbn/__init__.py
ahmedelsany12_pda-1.1.3.dist-info/METADATA
ahmedelsany12_pda-1.1.3.dist-info/WHEEL
ahmedelsany12_pda-1.1.3.dist-info/top_level.txt
ahmedelsany12_pda-1.1.3.dist-info/RECORD
