Metadata-Version: 2.4
Name: ahmedelsany12_pda
Version: 1.1.3
Summary: A simple PDA simulator for a^n b^n
Author-email: Ahmed Elsany <ahmedelsany12@gmail.com>
License: MIT
Classifier: Programming Language :: Python :: 3
Classifier: License :: OSI Approved :: MIT License
Classifier: Operating System :: OS Independent
Requires-Python: >=3.7
